chop/__init__.py
chop/cli.py
chop/operations.py
chop/output.py
chop/pipeline.py
tests/__init__.py
tests/test_chop.py
chop_img-0.5.0.dist-info/METADATA
chop_img-0.5.0.dist-info/WHEEL
chop_img-0.5.0.dist-info/entry_points.txt
chop_img-0.5.0.dist-info/top_level.txt
chop_img-0.5.0.dist-info/RECORD
