Metadata-Version: 2.4
Name: chop-img
Version: 0.5.0
Summary: Unix-philosophy image manipulation CLI with JSON piping
Author-email: Alexander Towell <queelius@gmail.com>
License-Expression: MIT
Project-URL: Homepage, https://github.com/queelius/chop
Project-URL: Repository, https://github.com/queelius/chop
Keywords: terminal,image,manipulation,pipeline,unix,visualization
Classifier: Development Status :: 3 - Alpha
Classifier: Environment :: Console
Classifier: Intended Audience :: Developers
Classifier: Operating System :: OS Independent
Classifier: Programming Language :: Python :: 3
Classifier: Programming Language :: Python :: 3.10
Classifier: Programming Language :: Python :: 3.11
Classifier: Programming Language :: Python :: 3.12
Classifier: Topic :: Multimedia :: Graphics
Classifier: Topic :: Terminals
Requires-Python: >=3.10
Requires-Dist: numpy>=1.20
Requires-Dist: pillow>=9.0
